dt_invariants/__init__.py
dt_invariants/src/__init__.py
dt_invariants/src/categories/__init__.py
dt_invariants/src/categories/abelian_category.py
dt_invariants/src/categories/slicing.py
dt_invariants/src/examples/__init__.py
dt_invariants/src/examples/quiver.py
dt_invariants/src/linear_algebra/__init__.py
dt_invariants/src/linear_algebra/central_charge.py
dt_invariants/src/linear_algebra/cone.py
dt_invariants/src/linear_algebra/dimension_vector.py
dt_invariants/src/linear_algebra/pairing.py
dt_invariants/src/linear_algebra/phase.py
dt_invariants/src/linear_algebra/standard_cone.py
dt_invariants/src/motives/__init__.py
dt_invariants/src/motives/dt_invariants.py
dt_invariants/src/motives/exp.py
dt_invariants/src/motives/gl.py
dt_invariants/src/motives/graded_motive.py
dt_invariants/src/motives/log.py
dt_invariants/src/motives/motive_of_semistables.py
dt_invariants/src/motives/motivic_series.py
dt_invariants/src/motives/sliced_motive.py
dt_invariants/src/motives/symbols.py
dt_invariants/src/motives/types.py
dt_invariants/src/stability/__init__.py
dt_invariants/src/stability/stability_condition.py
dt_invariants-0.2.0.dist-info/LICENSE.txt
dt_invariants-0.2.0.dist-info/METADATA
dt_invariants-0.2.0.dist-info/WHEEL
dt_invariants-0.2.0.dist-info/top_level.txt
dt_invariants-0.2.0.dist-info/RECORD
