Metadata-Version: 2.1
Name: dt-invariants
Version: 0.2.0
Summary: A set of tools to compute DT invariants of quivers
Home-page: https://github.com/s-meinhardt/dt-invariants
Author: Sven Meinhardt
Author-email: sven@meinhardt.ai
License: GNU GPLv3
Platform: UNKNOWN
Classifier: License :: OSI Approved :: GNU General Public License v3 (GPLv3)
Classifier: Programming Language :: Python :: 3.9
Classifier: Operating System :: OS Independent
Requires-Python: >=3.9
License-File: LICENSE.txt
Requires-Dist: sympy (>=1.11.1)
Provides-Extra: dev
Requires-Dist: pytest (>=7.0) ; extra == 'dev'
Requires-Dist: twine (>=4.0.2) ; extra == 'dev'
